furo/__init__.py
furo/_demo_module.py
furo/assets/scripts/furo.js
furo/assets/scripts/gumshoe-patched.js
furo/assets/styles/_scaffold.sass
furo/assets/styles/_shame.sass
furo/assets/styles/base/_index.sass
furo/assets/styles/base/_print.sass
furo/assets/styles/base/_screen-readers.sass
furo/assets/styles/base/_theme.sass
furo/assets/styles/base/_typography.sass
furo/assets/styles/components/_footer.sass
furo/assets/styles/components/_index.sass
furo/assets/styles/components/_search.sass
furo/assets/styles/components/_sidebar.sass
furo/assets/styles/components/_table_of_contents.sass
furo/assets/styles/content/_admonitions.sass
furo/assets/styles/content/_api.sass
furo/assets/styles/content/_blocks.sass
furo/assets/styles/content/_captions.sass
furo/assets/styles/content/_code.sass
furo/assets/styles/content/_footnotes.sass
furo/assets/styles/content/_gui-labels.sass
furo/assets/styles/content/_images.sass
furo/assets/styles/content/_index.sass
furo/assets/styles/content/_indexes.sass
furo/assets/styles/content/_lists.sass
furo/assets/styles/content/_math.sass
furo/assets/styles/content/_misc.sass
furo/assets/styles/content/_rubrics.sass
furo/assets/styles/content/_sidebar.sass
furo/assets/styles/content/_tables.sass
furo/assets/styles/content/_target.sass
furo/assets/styles/extensions/_copybutton.sass
furo/assets/styles/extensions/_index.sass
furo/assets/styles/extensions/_readthedocs.sass
furo/assets/styles/extensions/_sphinx-design.sass
furo/assets/styles/extensions/_sphinx-inline-tabs.sass
furo/assets/styles/extensions/_sphinx-panels.sass
furo/assets/styles/furo-extensions.sass
furo/assets/styles/furo.sass
furo/assets/styles/variables/_admonitions.scss
furo/assets/styles/variables/_colors.scss
furo/assets/styles/variables/_fonts.scss
furo/assets/styles/variables/_icons.scss
furo/assets/styles/variables/_index.sass
furo/assets/styles/variables/_layout.scss
furo/assets/styles/variables/_spacing.scss
furo/navigation.py
furo/sphinxext.py
furo/theme/furo/base.html
furo-2024.7.18.dist-info/LICENSE
furo-2024.7.18.dist-info/METADATA
furo-2024.7.18.dist-info/WHEEL
furo-2024.7.18.dist-info/entry_points.txt
furo-2024.7.18.dist-info/RECORD