Metadata-Version: 2.1
Name: furo
Version: 2024.7.18
Summary: A clean customisable Sphinx documentation theme.
Author-Email: Pradyun Gedam <mail@pradyunsg.me>
License: Copyright (c) 2020 Pradyun Gedam <mail@pradyunsg.me>
Classifier: Framework :: Sphinx
Classifier: Framework :: Sphinx :: Theme
Classifier: Development Status :: 5 - Production/Stable
Classifier: License :: OSI Approved :: MIT License
Classifier: Environment :: Web Environment
Classifier: Intended Audience :: Developers
Classifier: Programming Language :: Python :: 3
Classifier: Programming Language :: Python :: 3.8
Classifier: Programming Language :: Python :: 3.9
Classifier: Programming Language :: Python :: 3.10
Classifier: Programming Language :: Python :: 3.11
Classifier: Programming Language :: Python :: 3.12
Classifier: Operating System :: OS Independent
Classifier: Topic :: Documentation
Classifier: Topic :: Software Development :: Documentation
Project-URL: Github, https://github.com/pradyunsg/furo
Requires-Python: >=3.8
Requires-Dist: beautifulsoup4
Requires-Dist: sphinx<8.0,>=6.0
Requires-Dist: sphinx-basic-ng>=1.0.0.beta2
Requires-Dist: pygments>=2.7
